{
  "$schema": "https://developer.microsoft.com/json-schemas/spfx-build/package-solution.schema.json",
  "solution": {
    "name": "leave-request-client-side-solution",
    "id": "0f08089c-2442-444a-aae0-1ff031730fcc",
    "version": "1.0.0.0",
    "includeClientSideAssets": true,
    "skipFeatureDeployment": true,
    "isDomainIsolated": false,
    "developer": {
      "name": "",
      "websiteUrl": "",
      "privacyUrl": "",
      "termsOfUseUrl": "",
      "mpnId": "Undefined-1.13.1"
    }
  },
  "paths": {
    "zippedPackage": "solution/leave-request.sppkg"
  }
}
